nomad_normalizer_plugin_system-1.0.4.dist-info/licenses/LICENSE
systemnormalizer/__init__.py
systemnormalizer/nomad_plugin.yaml
systemnormalizer/normalizer.py
nomad_normalizer_plugin_system-1.0.4.dist-info/METADATA
nomad_normalizer_plugin_system-1.0.4.dist-info/WHEEL
nomad_normalizer_plugin_system-1.0.4.dist-info/entry_points.txt
nomad_normalizer_plugin_system-1.0.4.dist-info/top_level.txt
nomad_normalizer_plugin_system-1.0.4.dist-info/RECORD
